pyzmp/__init__.py
pyzmp/__main__.py
pyzmp/_version.py
pyzmp/coprocess.py
pyzmp/exceptions.py
pyzmp/helpers.py
pyzmp/master.py
pyzmp/message.py
pyzmp/node.py
pyzmp/service.py
pyzmp/service_pb2.py
pyzmp/topic.py
pyzmp/tests/__init__.py
pyzmp/tests/profile_node.py
pyzmp/tests/test_coprocess.py
pyzmp/tests/test_message.py
pyzmp/tests/test_node.py
pyzmp/tests/test_service.py
pyzmp-0.0.17.dist-info/METADATA
pyzmp-0.0.17.dist-info/RECORD
pyzmp-0.0.17.dist-info/WHEEL
pyzmp-0.0.17.dist-info/entry_points.txt
pyzmp-0.0.17.dist-info/pbr.json
pyzmp-0.0.17.dist-info/top_level.txt
