Metadata-Version: 1.0
Name: pyzmp
Version: 0.0.17
Summary: ZeroMq based multiprocessing framework.
Home-page: http://github.com/asmodehn/pyzmp
Author: AlexV
Author-email: asmodehn@gmail.com
License: BSD
Platform: UNKNOWN
